generate_reqs/__init__.py
generate_reqs/cli.py
generate_reqs-1.0.0.dist-info/licenses/LICENSE
generate_reqs-1.0.0.dist-info/METADATA
generate_reqs-1.0.0.dist-info/WHEEL
generate_reqs-1.0.0.dist-info/entry_points.txt
generate_reqs-1.0.0.dist-info/top_level.txt
generate_reqs-1.0.0.dist-info/RECORD
